{
  "id": "ContractDelivery",
  "title": "ContractDelivery",
  "example": {
    "data": {
      "tradeSymbol": "IRON_ORE",
      "destination": "X1-OE-PM",
      "units": 10000,
      "fulfilled": 500
    }
  },
  "extensions": {
    "x-stoplight": {
      "id": "qmlqni8bb86az"
    },
    "x-examples": {
      "example-1": {
        "data": {
          "tradeSymbol": "IRON_ORE",
          "destination": "X1-OE-PM",
          "units": 10000,
          "fulfilled": 500
        }
      }
    }
  },
  "type": "object",
  "properties": {
    "data": {
      "$ref": "Data.json"
    }
  },
  "required": [
    "data"
  ]
}
