{
  "id": "Trade",
  "title": "Trade",
  "example": {
    "waypointSymbol": "X1-OE-PM",
    "tradeSymbol": "MICROPROCESSORS",
    "credits": 843,
    "units": 1
  },
  "extensions": {
    "x-stoplight": {
      "id": "yz4digw1bhqsh"
    },
    "x-examples": {
      "example-1": {
        "waypointSymbol": "X1-OE-PM",
        "tradeSymbol": "MICROPROCESSORS",
        "credits": -843,
        "units": 1
      }
    }
  },
  "type": "object",
  "properties": {
    "waypointSymbol": {
      "type": "string",
      "minLength": 1
    },
    "tradeSymbol": {
      "type": "string",
      "minLength": 1
    },
    "credits": {
      "type": "integer",
      "format": "int32"
    },
    "units": {
      "type": "integer",
      "format": "int32"
    }
  },
  "required": [
    "waypointSymbol",
    "tradeSymbol",
    "credits",
    "units"
  ]
}
